pics/__init__.py
pics/pic.py
pics-5.3.3.dist-info/METADATA
pics-5.3.3.dist-info/WHEEL
pics-5.3.3.dist-info/top_level.txt
pics-5.3.3.dist-info/RECORD
