Metadata-Version: 2.2
Name: pics
Version: 5.3.3
Summary: for cut picture
Home-page: https://gitee.com/teark/pictools.git
Author: TEARK
Author-email: 913355434@qq.com
Classifier: Programming Language :: Python :: 3
Classifier: License :: OSI Approved :: MIT License
Classifier: Operating System :: OS Independent
Requires-Python: >=3.6
Dynamic: author
Dynamic: author-email
Dynamic: classifier
Dynamic: description
Dynamic: description-content-type
Dynamic: home-page
Dynamic: requires-python
Dynamic: summary
